ltl_augmentation/__init__.py
ltl_augmentation/ltl_augmentation.cpython-312-x86_64-linux-musl.so
ltl_augmentation.libs/libgcc_s-2298274a.so.1
ltl_augmentation-0.1.0.dist-info/METADATA
ltl_augmentation-0.1.0.dist-info/WHEEL
ltl_augmentation-0.1.0.dist-info/RECORD
