Metadata-Version: 2.4
Name: ltl_augmentation
Version: 0.1.0
Classifier: Programming Language :: Rust
Classifier: Programming Language :: Python :: 3
Classifier: Programming Language :: Python :: 3.9
Classifier: Programming Language :: Python :: 3.10
Classifier: Programming Language :: Python :: 3.11
Classifier: Programming Language :: Python :: 3.12
Classifier: Operating System :: POSIX :: Linux
Requires-Dist: ruff~=0.8.0 ; extra == 'dev'
Provides-Extra: dev
Summary: A Toolbox for Augmenting LTL Specifications with External Knowledge
Keywords: simplification,augmentation,temporal logic,specifications
Author-email: Cyber-Physical Systems Group - Technical University of Munich <commonroad@lists.lrz.de>
Requires-Python: >=3.7
